quenouille/__init__.py
quenouille/constants.py
quenouille/exceptions.py
quenouille/imap.py
quenouille/utils.py
quenouille-1.9.1.dist-info/LICENSE.txt
quenouille-1.9.1.dist-info/METADATA
quenouille-1.9.1.dist-info/WHEEL
quenouille-1.9.1.dist-info/top_level.txt
quenouille-1.9.1.dist-info/zip-safe
quenouille-1.9.1.dist-info/RECORD
