Metadata-Version: 2.1
Name: quenouille
Version: 1.9.1
Summary: A library of multithreaded iterator workflows.
Home-page: http://github.com/medialab/quenouille
Author: Guillaume Plique
Author-email: kropotkinepiotr@gmail.com
License: MIT
Keywords: url
Platform: UNKNOWN
Requires-Python: >=3.5
Requires-Dist: typing-extensions ; python_version<'3.8'
